brownian_diffuser/__init__.py
brownian_diffuser/_core/__init__.py
brownian_diffuser/_core/_brownian_diffuser.py
brownian_diffuser/_core/_brownian_motion.py
brownian_diffuser/_core/_nn_int.py
brownian_diffuser/_core/_time.py
brownian_diffuser-0.0.2.dist-info/LICENSE
brownian_diffuser-0.0.2.dist-info/METADATA
brownian_diffuser-0.0.2.dist-info/WHEEL
brownian_diffuser-0.0.2.dist-info/top_level.txt
brownian_diffuser-0.0.2.dist-info/RECORD
