Metadata-Version: 2.1
Name: brownian-diffuser
Version: 0.0.2
Summary: Brownian diffuser
Home-page: https://github.com/mvinyard/brownian-diffuser
Author: Michael E. Vinyard - Harvard University - Broad Institute of MIT and Harvard - Massachussetts General Hospital
Author-email: mvinyard@broadinstitute.org
License: MIT
Classifier: Development Status :: 2 - Pre-Alpha
Classifier: Programming Language :: Python :: 3.7
Classifier: Intended Audience :: Science/Research
Classifier: Topic :: Scientific/Engineering :: Bio-Informatics
Requires-Python: >3.7.0
License-File: LICENSE
Requires-Dist: torch (>=1.12.0)
Requires-Dist: autodevice (>=0.0.2)
